XMLAccessor/XMLAccessor.py
XMLAccessor/__init__.py
xmlaccessor-1.0.0.dist-info/licenses/LICENSE
xmlaccessor-1.0.0.dist-info/METADATA
xmlaccessor-1.0.0.dist-info/WHEEL
xmlaccessor-1.0.0.dist-info/top_level.txt
xmlaccessor-1.0.0.dist-info/RECORD
