Metadata-Version: 2.4
Name: XMLAccessor
Version: 1.0.0
Summary: Populate Python Classes from XML
Author-email: Phillip Harry T <philliptinsley44@gmail.com>
License: Apache NON-AI License, Version 2.0
Keywords: XML,xml,lxml,cast,populate,nested,xmlaccessor
Classifier: License :: Other/Proprietary License
Classifier: Programming Language :: Python
Classifier: Programming Language :: Python :: 3
Classifier: Intended Audience :: Information Technology
Requires-Python: >=3.8
License-File: LICENSE
Dynamic: license-file
